emulator_tools-0.1.0.data/scripts/emulator-tools
tools/bigtable.py
tools/pubsub.py
emulator_tools-0.1.0.dist-info/LICENSE
emulator_tools-0.1.0.dist-info/METADATA
emulator_tools-0.1.0.dist-info/WHEEL
emulator_tools-0.1.0.dist-info/top_level.txt
emulator_tools-0.1.0.dist-info/RECORD
