Metadata-Version: 2.1
Name: emulator-tools
Version: 0.1.0
Summary: Set of tools for interacting with Google Cloud Emulators
Home-page: https://github.com/aylien/emulator-tools
Author: AYLIEN Engineering
Author-email: eng-team@aylien.com
License: UNKNOWN
Platform: UNKNOWN
Classifier: Programming Language :: Python :: 3
Classifier: License :: OSI Approved :: MIT License
Classifier: Operating System :: OS Independent
Requires-Dist: google-cloud-pubsub (==1.1.0)
Requires-Dist: google-cloud-bigtable (==1.2.1)
Requires-Dist: google-cloud-core (==1.1.0)
